xr_robot_teleop_server/__about__.py
xr_robot_teleop_server/__init__.py
xr_robot_teleop_server/cli.py
xr_robot_teleop_server/logging.py
xr_robot_teleop_server/schemas/__init__.py
xr_robot_teleop_server/schemas/body_pose.py
xr_robot_teleop_server/schemas/openxr_skeletons.py
xr_robot_teleop_server/sources/__init__.py
xr_robot_teleop_server/sources/base.py
xr_robot_teleop_server/sources/ffmpeg_source.py
xr_robot_teleop_server/sources/gopro_source.py
xr_robot_teleop_server/sources/opencv_source.py
xr_robot_teleop_server/streaming/__init__.py
xr_robot_teleop_server/streaming/webrtc_server.py
xr_robot_teleop_server/transforms/__init__.py
xr_robot_teleop_server/transforms/base.py
xr_robot_teleop_server/transforms/equilib_transforms.py
xr_robot_teleop_server/utils/__init__.py
xr_robot_teleop_server/utils/codecs.py
xr_robot_teleop_server/utils/coordinate.py
xr_robot_teleop_server/utils/frame.py
xr_robot_teleop_server-0.1.8.dist-info/METADATA
xr_robot_teleop_server-0.1.8.dist-info/WHEEL
xr_robot_teleop_server-0.1.8.dist-info/entry_points.txt
xr_robot_teleop_server-0.1.8.dist-info/licenses/LICENSE
xr_robot_teleop_server-0.1.8.dist-info/RECORD
