Metadata-Version: 2.4
Name: xr-robot-teleop-server
Version: 0.1.8
Summary: a robot teleoperation server for XR headsets
Project-URL: Homepage, https://github.com/yunho-c/xr-robot-teleop-server
Project-URL: Repository, https://github.com/yunho-c/xr-robot-teleop-server
Project-URL: Bug Tracker, https://github.com/yunho-c/xr-robot-teleop-server/issues
Author-email: Yunho Cho <github@yunhocho.com>
License: MIT License
License-File: LICENSE
Classifier: Development Status :: 3 - Alpha
Classifier: Intended Audience :: Developers
Classifier: License :: OSI Approved :: MIT License
Classifier: Operating System :: OS Independent
Classifier: Programming Language :: Python :: 3.10
Classifier: Programming Language :: Python :: 3.11
Classifier: Programming Language :: Python :: 3.12
Classifier: Programming Language :: Python :: 3.13
Requires-Python: >=3.10
Requires-Dist: aiortc
Requires-Dist: fastapi
Requires-Dist: loguru
Requires-Dist: numpy
Requires-Dist: opencv-python
Requires-Dist: pillow
Requires-Dist: pyequilib
Requires-Dist: python-multipart
Requires-Dist: scipy
Requires-Dist: torch
Requires-Dist: uvicorn
Provides-Extra: dev
Requires-Dist: hatch; extra == 'dev'
Requires-Dist: mypy>=1.0; extra == 'dev'
Requires-Dist: pre-commit; extra == 'dev'
Requires-Dist: pytest-cov; extra == 'dev'
Requires-Dist: pytest>=8.0; extra == 'dev'
Requires-Dist: ruff; extra == 'dev'
Provides-Extra: viz
Requires-Dist: matplotlib; extra == 'viz'
Requires-Dist: rerun-sdk; extra == 'viz'
